[
  {
    "key": "clothing",
    "icon": "blip_shop_tailor",
    "locations": [
      {"text": "Bekleidungsgeschäft", "x": -28.8686168827153, "y": 118.40702119817779},
      {"text": "Bekleidungsgeschäft", "x": -51.5234375, "y": 106.2734375},
      {"text": "Bekleidungsgeschäft", "x": -25.9296875, "y": 90.21875},
      {"text": "Bekleidungsgeschäft", "x": -42.8515625, "y": 157.0625},
      {"text": "Bekleidungsgeschäft", "x": -55.20138786507209, "y": 157.04087137512175},
      {"text": "Bekleidungsgeschäft", "x": -83.6222154856465, "y": 131.96760543979212},
      {"text": "Bekleidungsgeschäft", "x": -69.6242459034597, "y": 83.44688889405606},
      {"text": "Bekleidungsgeschäft", "x": -83.63577072078837, "y": 99.43884397558907},
      {"text": "Bekleidungsgeschäft", "x": -81.71642660442204, "y": 150.95183630469603},
      {"text": "Bekleidungsgeschäft", "x": -104.32806361212285, "y": 54.43914217807016},
      {"text": "Bekleidungsgeschäft", "x": -109.169921875, "y": 26.1005859375}
    ]
  },
  {
    "key": "barber",
    "icon": "blip_shop_barber",
    "locations": [
      {"text": "Friseur", "x": -29.560140966551096, "y": 118.21598627356403},
      {"text": "Friseur", "x": -50.9296875, "y": 106.5078125},
      {"text": "Friseur", "x": -26.296875, "y": 90.3828125},
      {"text": "Friseur", "x": -43.234375, "y": 156.9296875},
      {"text": "Friseur", "x": -55.078125, "y": 156.96875},
      {"text": "Friseur", "x": -83.96875, "y": 131.65625},
      {"text": "Friseur", "x": -69.71875, "y": 83.4140625},
      {"text": "Friseur", "x": -81.8984375, "y": 152.515625},
      {"text": "Friseur", "x": -84.8828125, "y": 98.6484375},
      {"text": "Friseur", "x": -104.296875, "y": 54.1640625},
      {"text": "Friseur", "x": -109.140625, "y": 25.9375}
    ]
  },
  {
    "key": "fishing",
    "icon": "blip_shop_tackle",
    "locations": [
      {"text": "Ambarino Fischhändler", "x": -29.60706182522816, "y": 118.01601404253557},
      {"text": "Blackwater Fischhändler", "x": -84.84375, "y": 99.4453125},
      {"text": "Dunkelhain Fischhändler", "x": -27.140625, "y": 89.546875},
      {"text": "Rhodes Fischhändler", "x": -84, "y": 132.6796875},
      {"text": "Tumbleweed Fischhändler", "x": -108.671875, "y": 25.5625},
      {"text": "Van Horn Fischhändler", "x": -55.53125, "y": 157.6484375}
    ]
  },
  {
    "key": "seeds",
    "icon": "blip_summer_horse",
    "locations": [
      {"text": "Blumenladen Samen Verkauf", "x": -53.6875, "y": 107.2265625},
      {"text": "Dünger  & Samen Händler", "x": -68.8828125, "y": 105.390625},
      {"text": "Dünger & Samen Händler", "x": -81.5703125, "y": 133.21875},
      {"text": "Dünger & Samen Händler", "x": -101.3984375, "y": 72.671875},
      {"text": "Farmbedarf", "x": -53.7890625, "y": 107.390625},
      {"text": "Farmbedarf", "x": -83.3515625, "y": 132.0859375},
      {"text": "Farmbedarf", "x": -78.0859375, "y": 153.328125},
      {"text": "Farmbedarf", "x": -104.359375, "y": 54.078125},
      {"text": "Farmbedarf", "x": -108.8515625, "y": 25.1484375},
      {"text": "Farmbedarf", "x": -29.46318086373262, "y": 118.03605401327329}
    ]
  },
  {
    "key": "other",
    "icon": "blip_ambient_loan_shark",
    "locations": [
      {"text": "Stammesladen", "x": -29.017199601859343, "y": 118.13890200573742},
      {"text": "Make Up & Nette Dinge", "x": -28.40625, "y": 118.625},
      {"text": "Make Up & Nette Dinge & Kleider", "x": -82.71875, "y": 151.3046875}
    ]
  },
  {
    "key": "furniture",
    "icon": "blip_fence_building",
    "locations": [
      {"text": "Möbelgeschäft", "x": -86.0234375, "y": 152.0859375},
      {"text": "Möbelgeschäft", "x": -103.21875, "y": 54.2109375}
    ]
  },
  {
    "key": "goods",
    "icon": "blip_shop_store",
    "locations": [
      {"text": "St. Denis Warenankauf", "x": -82.6328125, "y": 155.34375},
      {"text": "Tumbleweed Warenankauf", "x": -108.96875, "y": 26.0390625}
    ]
  },
  {
    "key": "gunoil",
    "icon": "blip_decision",
    "locations": [
      {"text": "Waffenöl", "x": -42.5390625, "y": 155.546875},
      {"text": "Waffenöl", "x": -104.203125, "y": 53.3359375}
    ]
  },
  {
    "key": "weapons",
    "icon": "blip_mp_playstyle_offensive",
    "locations": [
      {"text": "Waffenladen", "x": -43.125, "y": 157.0078125},
      {"text": "Waffenladen", "x": -84.078125, "y": 131.9140625},
      {"text": "Waffenladen", "x": -70.1484375, "y": 82.6640625},
      {"text": "Waffenladen", "x": -83.703125, "y": 99.0390625},
      {"text": "Waffenladen", "x": -83.5234375, "y": 153.5234375},
      {"text": "Waffenladen", "x": -103.8828125, "y": 54.375},
      {"text": "Waffenladen", "x": -109.5859375, "y": 25.7578125}
    ]
  },
  {
    "key": "bathhouse",
    "icon": "blip_bath_house",
    "locations": [
      {"text": "Badehaus", "x": -51.765625, "y": 106.3125},
      {"text": "Badehaus", "x": -42.9296875, "y": 157.0703125},
      {"text": "Badehaus", "x": -54.7109375, "y": 157.5859375},
      {"text": "Badehaus", "x": -85.0078125, "y": 132.109375},
      {"text": "Badehaus", "x": -69.3671875, "y": 83.03125},
      {"text": "Badehaus", "x": -83.9375, "y": 98.5078125},
      {"text": "Badehaus", "x": -82.5859375, "y": 152.203125}
    ]
  },
  {
    "key": "pets",
    "icon": "blip_animal",
    "locations": [
      {"text": "Haustier Händler", "x": -49, "y": 105.1875},
      {"text": "Haustier Händler", "x": -51.390625, "y": 157.703125},
      {"text": "Haustier Händler", "x": -83.6327930167607, "y": 96.3906599074704},
      {"text": "Haustier Händler", "x": -110.90625, "y": 25.2421875}
    ]
  },
  {
    "key": "stationery",
    "icon": "blip_event_riggs_camp",
    "locations": [
      {"text": "Schreibwaren", "x": -83.140625, "y": 153.28125},
      {"text": "Schreibwaren", "x": -109.4609375, "y": 25.4765625}
    ]
  },
  {
    "key": "equipment",
    "icon": "blip_mp_ugc",
    "locations": [
      {"text": "Förster & Minenbedarf", "x": -42.6484375, "y": 154.8125},
      {"text": "Förster & Minenbedarf", "x": -62.26748948457209, "y": 75.23874369867633},
      {"text": "Förster & Minenbedarf", "x": -114.28125, "y": 18.890625},
      {"text": "Försterei Bedarf", "x": -51.9140625, "y": 107.6015625}
    ]
  },
  {
    "key": "hotel",
    "icon": "blip_hotel_bed",
    "locations": [
      {"text": "Hotelzimmer", "x": -82.6640625, "y": 152.25},
      {"text": "Hotelzimmer", "x": -51.6875, "y": 106.2734375}
    ]
  }
]